ggplotly/__init__.py
ggplotly/aes.py
ggplotly/aesthetic_mapper.py
ggplotly/constants.py
ggplotly/data_utils.py
ggplotly/datasets.py
ggplotly/exceptions.py
ggplotly/facets.py
ggplotly/ggplot.py
ggplotly/ggtitle.py
ggplotly/guides.py
ggplotly/layer.py
ggplotly/limits.py
ggplotly/map_data.py
ggplotly/positions.py
ggplotly/themes.py
ggplotly/trace_builders.py
ggplotly/utils.py
ggplotly/coords/__init__.py
ggplotly/coords/coord_base.py
ggplotly/coords/coord_cartesian.py
ggplotly/coords/coord_fixed.py
ggplotly/coords/coord_flip.py
ggplotly/coords/coord_polar.py
ggplotly/coords/coord_sf.py
ggplotly/data/commodity_prices.csv
ggplotly/data/diamonds.csv
ggplotly/data/economics.csv
ggplotly/data/economics_long.csv
ggplotly/data/faithfuld.csv
ggplotly/data/iris.csv
ggplotly/data/luv_colours.csv
ggplotly/data/midwest.csv
ggplotly/data/mpg.csv
ggplotly/data/msleep.csv
ggplotly/data/mtcars.csv
ggplotly/data/presidential.csv
ggplotly/data/seals.csv
ggplotly/data/txhousing.csv
ggplotly/data/us_flights_edges.csv
ggplotly/data/us_flights_nodes.csv
ggplotly/geoms/__init__.py
ggplotly/geoms/geom_abline.py
ggplotly/geoms/geom_acf.py
ggplotly/geoms/geom_area.py
ggplotly/geoms/geom_bar.py
ggplotly/geoms/geom_base.py
ggplotly/geoms/geom_boxplot.py
ggplotly/geoms/geom_candlestick.py
ggplotly/geoms/geom_col.py
ggplotly/geoms/geom_contour.py
ggplotly/geoms/geom_contour_filled.py
ggplotly/geoms/geom_density.py
ggplotly/geoms/geom_edgebundle.py
ggplotly/geoms/geom_errorbar.py
ggplotly/geoms/geom_fanchart.py
ggplotly/geoms/geom_histogram.py
ggplotly/geoms/geom_hline.py
ggplotly/geoms/geom_jitter.py
ggplotly/geoms/geom_label.py
ggplotly/geoms/geom_line.py
ggplotly/geoms/geom_lines.py
ggplotly/geoms/geom_map.py
ggplotly/geoms/geom_norm.py
ggplotly/geoms/geom_pacf.py
ggplotly/geoms/geom_path.py
ggplotly/geoms/geom_point.py
ggplotly/geoms/geom_point_3d.py
ggplotly/geoms/geom_qq.py
ggplotly/geoms/geom_qq_line.py
ggplotly/geoms/geom_range.py
ggplotly/geoms/geom_rect.py
ggplotly/geoms/geom_ribbon.py
ggplotly-0.4.1.dist-info/licenses/LICENSE
ggplotly-0.4.1.dist-info/METADATA
ggplotly-0.4.1.dist-info/WHEEL
ggplotly-0.4.1.dist-info/top_level.txt
ggplotly-0.4.1.dist-info/RECORD
