Metadata-Version: 2.4
Name: ggplotly
Version: 0.4.1
Summary: A grammar of graphics for Python built on Plotly
Author: Ben Cho
License: MIT
Project-URL: Homepage, https://github.com/bbcho/ggplotly
Project-URL: Documentation, https://bbcho.github.io/ggplotly
Project-URL: Repository, https://github.com/bbcho/ggplotly
Project-URL: Issues, https://github.com/bbcho/ggplotly/issues
Project-URL: Roadmap, https://github.com/bbcho/ggplotly/blob/main/ROADMAP.md
Keywords: ggplot,ggplot2,plotly,visualization,data visualization,grammar of graphics,plotting,charts,graphs
Classifier: Development Status :: 4 - Beta
Classifier: Intended Audience :: Developers
Classifier: Intended Audience :: Science/Research
Classifier: License :: OSI Approved :: MIT License
Classifier: Operating System :: OS Independent
Classifier: Programming Language :: Python :: 3
Classifier: Programming Language :: Python :: 3.9
Classifier: Programming Language :: Python :: 3.10
Classifier: Programming Language :: Python :: 3.11
Classifier: Programming Language :: Python :: 3.12
Classifier: Programming Language :: Python :: 3.13
Classifier: Programming Language :: Python :: 3.14
Classifier: Topic :: Scientific/Engineering :: Visualization
Requires-Python: >=3.9
License-File: LICENSE
Requires-Dist: pandas>=1.3.0
Requires-Dist: plotly>=5.0.0
Requires-Dist: numpy>=1.20.0
Requires-Dist: scikit-learn>=1.0.0
Requires-Dist: scipy>=1.7.0
Requires-Dist: statsmodels>=0.13.0
Provides-Extra: dev
Requires-Dist: pytest>=7.0.0; extra == "dev"
Requires-Dist: pytest-cov>=4.0.0; extra == "dev"
Requires-Dist: pytest-ruff>=0.4.0; extra == "dev"
Requires-Dist: nbmake>=1.5.0; extra == "dev"
Requires-Dist: black>=23.0.0; extra == "dev"
Requires-Dist: ruff>=0.1.0; extra == "dev"
Requires-Dist: mypy>=1.0.0; extra == "dev"
Provides-Extra: docs
Requires-Dist: mkdocs>=1.5.0; extra == "docs"
Requires-Dist: mkdocs-material>=9.0.0; extra == "docs"
Requires-Dist: mkdocstrings>=0.24.0; extra == "docs"
Requires-Dist: mkdocstrings-python>=1.0.0; extra == "docs"
Requires-Dist: mkdocs-jupyter>=0.24.0; extra == "docs"
Requires-Dist: nbconvert>=7.0.0; extra == "docs"
Requires-Dist: ipykernel>=6.0.0; extra == "docs"
Provides-Extra: geo
Requires-Dist: geopandas>=0.12.0; extra == "geo"
Requires-Dist: shapely>=2.0.0; extra == "geo"
Provides-Extra: network
Requires-Dist: igraph>=0.10.0; extra == "network"
Requires-Dist: searoute>=1.0.0; extra == "network"
Provides-Extra: all
Requires-Dist: ggplotly[dev,docs,geo,network]; extra == "all"
Dynamic: license-file
